LICENSE
README.md
kubitdb.py
setup.py
kubitdb.egg-info/PKG-INFO
kubitdb.egg-info/SOURCES.txt
kubitdb.egg-info/dependency_links.txt
kubitdb.egg-info/top_level.txt