Metadata-Version: 2.1
Name: kubitdb
Version: 0.2
Summary: Python KubitDB Modülü
Home-page: https://github.com/DeveloperKubilay/pythonkubitdb
Author: kubilaytr
Author-email: kullanici@example.com
License: MIT
License-File: LICENSE
